Metadata-Version: 2.1
Name: food-project
Version: 1.6
Summary: An example package.
Home-page: https://github.com/shuygena/food_project
Author: Zukhra Khubieva & Vadim Petruhnenko \ shuygena
Author-email: hubieva123@icloud.com
License: UNKNOWN
Platform: UNKNOWN
Classifier: Development Status :: 3 - Alpha
Classifier: Intended Audience :: Developers
Classifier: Operating System :: Unix
Classifier: Operating System :: POSIX
Classifier: Programming Language :: Python
Classifier: Programming Language :: Python :: 3.8
Classifier: Programming Language :: Python :: Implementation :: CPython
Classifier: Programming Language :: Python :: Implementation :: PyPy
